MANIFEST.in
README.md
setup.cfg
setup.py
qhub_ops/__init__.py
qhub_ops/__main__.py
qhub_ops/deploy.py
qhub_ops/utils.py
qhub_ops.egg-info/PKG-INFO
qhub_ops.egg-info/SOURCES.txt
qhub_ops.egg-info/dependency_links.txt
qhub_ops.egg-info/entry_points.txt
qhub_ops.egg-info/requires.txt
qhub_ops.egg-info/top_level.txt
qhub_ops/cli/__init__.py
qhub_ops/cli/deploy.py
qhub_ops/cli/render.py
qhub_ops/provider/__init__.py
qhub_ops/provider/terraform.py
qhub_ops/provider/cloud/__init__.py
qhub_ops/provider/cloud/amazon_web_services.py
qhub_ops/provider/cloud/digital_ocean.py
qhub_ops/provider/cloud/google_cloud.py
qhub_ops/provider/dns/__init__.py
qhub_ops/provider/dns/cloudflare.py
qhub_ops/provider/oauth/__init__.py
qhub_ops/provider/oauth/auth0.py
qhub_ops/render/__init__.py
qhub_ops/render/jinja.py
qhub_ops/template/cookiecutter.json
qhub_ops/template/hooks/post_gen_project.py
qhub_ops/template/hooks/pre_gen_project.py
qhub_ops/template/hooks/prompt_gen_project.py
qhub_ops/template/{{ cookiecutter.repo_directory }}/.gitignore
qhub_ops/template/{{ cookiecutter.repo_directory }}/README.md
qhub_ops/template/{{ cookiecutter.repo_directory }}/.github/workflows/image-pr.yaml
qhub_ops/template/{{ cookiecutter.repo_directory }}/.github/workflows/image.yaml
qhub_ops/template/{{ cookiecutter.repo_directory }}/.github/workflows/jupyterhub-pr.yaml
qhub_ops/template/{{ cookiecutter.repo_directory }}/.github/workflows/jupyterhub.yaml
qhub_ops/template/{{ cookiecutter.repo_directory }}/.github/workflows/qhub-ops.yaml
qhub_ops/template/{{ cookiecutter.repo_directory }}/docs/configuration.md
qhub_ops/template/{{ cookiecutter.repo_directory }}/docs/infrastructure.md
qhub_ops/template/{{ cookiecutter.repo_directory }}/docs/installation.md
qhub_ops/template/{{ cookiecutter.repo_directory }}/docs/maintenance.md
qhub_ops/template/{{ cookiecutter.repo_directory }}/docs/theming.md
qhub_ops/template/{{ cookiecutter.repo_directory }}/image/Dockerfile.dask-worker
qhub_ops/template/{{ cookiecutter.repo_directory }}/image/Dockerfile.jupyterhub
qhub_ops/template/{{ cookiecutter.repo_directory }}/image/Dockerfile.jupyterlab
qhub_ops/template/{{ cookiecutter.repo_directory }}/image/README.md
