Metadata-Version: 2.1
Name: qhub-ops
Version: 0.1.8
Summary: Management of QHub on Cloud Infrastructure
Home-page: https://github.com/quansight/qhub-ops
Author: Quansight
License: UNKNOWN
Project-URL: Bug Reports, https://github.com/quansight/QHub
Project-URL: Source, https://github.com/quansight/QHub
Keywords: aws gcp do qhub
Platform: UNKNOWN
Classifier: Development Status :: 3 - Alpha
Classifier: Intended Audience :: Developers
Classifier: Topic :: Software Development :: Build Tools
Classifier: Programming Language :: Python :: 3
Classifier: Programming Language :: Python :: 3.6
Classifier: Programming Language :: Python :: 3.7
Classifier: Programming Language :: Python :: 3.8
Requires-Python: >=2.7, !=3.0.*, !=3.1.*, !=3.2.*, !=3.3.*, !=3.4.*, !=3.5.*, <4
Provides-Extra: dev
